glue3d/__init__.py
glue3d/data.py
glue3d/evaluate_answers.py
glue3d/generate_answers.py
glue3d/main.py
glue3d/evaluators/__init__.py
glue3d/evaluators/base.py
glue3d/evaluators/loaders.py
glue3d/evaluators/misc.py
glue3d/evaluators/phi3_5.py
glue3d/evaluators/qwen3.py
glue3d/models/__init__.py
glue3d/models/base.py
glue3d/models/hf.py
glue3d/models/llava.py
glue3d/models/llava_3d.py
glue3d/models/loaders.py
glue3d/models/minigpt3d.py
glue3d/models/phi_vision.py
glue3d/models/pointllm.py
glue3d/models/qwen.py
glue3d/models/shapellm.py
glue3d/models/text_only.py
glue3d-0.2.5.dist-info/licenses/LICENSE
glue3d-0.2.5.dist-info/METADATA
glue3d-0.2.5.dist-info/WHEEL
glue3d-0.2.5.dist-info/entry_points.txt
glue3d-0.2.5.dist-info/top_level.txt
glue3d-0.2.5.dist-info/RECORD
