Metadata-Version: 2.4
Name: glue3d
Version: 0.2.5
Summary: Official project for GLUE3D.
Author: Alessandro Raganato, Simone Melzi, Gabriella Pasi
Author-email: Giorgio Mariani <giorgiomariani94@gmail.com>
License-Expression: MIT
Project-URL: Homepage, https://github.com/giorgio-mariani/GLUE3D
Project-URL: Repository, https://github.com/giorgio-mariani/GLUE3D
Project-URL: Issues, https://github.com/giorgio-mariani/GLUE3D/issues
Keywords: benchmark,point cloud,multimodal,three-dimensional,3d
Requires-Python: >=3.10
License-File: LICENSE
Requires-Dist: numpy
Requires-Dist: transformers
Requires-Dist: huggingface_hub
Requires-Dist: pandas
Requires-Dist: datasets
Requires-Dist: sentence-transformers
Requires-Dist: nltk
Requires-Dist: scipy
Requires-Dist: click
Requires-Dist: rouge
Requires-Dist: llama-cpp-python
Requires-Dist: OpenEXR
Provides-Extra: blender
Requires-Dist: bpy==4.4.0; extra == "blender"
Provides-Extra: dev
Requires-Dist: pre-commit; extra == "dev"
Requires-Dist: black; extra == "dev"
Requires-Dist: pytest>=6.0.0; extra == "dev"
Dynamic: license-file
